plaintext_daw/__init__.py
plaintext_daw/cli.py
plaintext_daw/gui.py
plaintext_daw/lib.py
plaintext_daw-0.0.0.dist-info/METADATA
plaintext_daw-0.0.0.dist-info/WHEEL
plaintext_daw-0.0.0.dist-info/entry_points.txt
plaintext_daw-0.0.0.dist-info/top_level.txt
plaintext_daw-0.0.0.dist-info/RECORD
